thinking_prompt/__init__.py
thinking_prompt/app_info.py
thinking_prompt/dialog.py
thinking_prompt/display.py
thinking_prompt/history.py
thinking_prompt/layout.py
thinking_prompt/py.typed
thinking_prompt/session.py
thinking_prompt/settings_dialog.py
thinking_prompt/styles.py
thinking_prompt/thinking.py
thinking_prompt/types.py
thinking_prompt-0.2.3.dist-info/METADATA
thinking_prompt-0.2.3.dist-info/WHEEL
thinking_prompt-0.2.3.dist-info/licenses/LICENSE
thinking_prompt-0.2.3.dist-info/RECORD
