Metadata-Version: 2.4
Name: thinking-prompt
Version: 0.2.3
Summary: A prompt_toolkit extension that adds a thinking box above the prompt
Project-URL: Homepage, https://github.com/shoom1/thinking-prompt
Project-URL: Repository, https://github.com/shoom1/thinking-prompt
Author: Andrey Shiryaev
License-Expression: MIT
License-File: LICENSE
Keywords: ai,cli,prompt_toolkit,terminal,thinking
Classifier: Development Status :: 3 - Alpha
Classifier: Environment :: Console
Classifier: Intended Audience :: Developers
Classifier: License :: OSI Approved :: MIT License
Classifier: Operating System :: OS Independent
Classifier: Programming Language :: Python :: 3
Classifier: Programming Language :: Python :: 3.9
Classifier: Programming Language :: Python :: 3.10
Classifier: Programming Language :: Python :: 3.11
Classifier: Programming Language :: Python :: 3.12
Classifier: Topic :: Software Development :: Libraries :: Python Modules
Classifier: Topic :: Terminals
Requires-Python: >=3.9
Requires-Dist: prompt-toolkit>=3.0.0
Provides-Extra: all
Requires-Dist: pygments>=2.0; extra == 'all'
Requires-Dist: rich>=13.0; extra == 'all'
Provides-Extra: dev
Requires-Dist: mypy>=1.0; extra == 'dev'
Requires-Dist: pytest-asyncio>=0.21; extra == 'dev'
Requires-Dist: pytest-cov>=4.0; extra == 'dev'
Requires-Dist: pytest>=7.0; extra == 'dev'
Requires-Dist: ruff>=0.1.0; extra == 'dev'
Provides-Extra: rich
Requires-Dist: rich>=13.0; extra == 'rich'
